deadsea_optics/__init__.py
deadsea_optics/__main__.py
deadsea_optics/cli.py
deadsea_optics/gui.py
deadsea_optics/main_window.ui
deadsea_optics/py.typed
deadsea_optics/spectroscopy.py
deadsea_optics/ui_main_window.py
deadsea_optics/usb2000.py
deadsea_optics/usb2000plus.py
deadsea_optics/resources/app_icon.icns
deadsea_optics/resources/app_icon.ico
deadsea_optics/resources/app_icon.png
deadsea_optics/resources/app_icon.pxd
deadsea_optics/resources/app_icon_win.png
deadsea_optics/resources/create_icons.sh
deadsea_optics-1.0.0.dist-info/METADATA
deadsea_optics-1.0.0.dist-info/WHEEL
deadsea_optics-1.0.0.dist-info/entry_points.txt
deadsea_optics-1.0.0.dist-info/licenses/LICENSE
deadsea_optics-1.0.0.dist-info/RECORD
