Metadata-Version: 2.4
Name: deadsea-optics
Version: 1.0.0
Summary: Spectrosopy software using the legacy Ocean Optics USB2000(+) spectrometer.
Author-email: David Fokkema <davidfokkema@icloud.com>
License-File: LICENSE
Requires-Python: >=3.11
Requires-Dist: briefcase>=0.3.21
Requires-Dist: libusb-package>=1.0.26.2
Requires-Dist: matplotlib>=3.10.0
Requires-Dist: numpy>=2.2.1
Requires-Dist: plotext>=5.3.2
Requires-Dist: pyqtgraph>=0.13.7
Requires-Dist: pyside6-essentials>=6.8.1.1
Requires-Dist: pyusb>=1.3.1
Requires-Dist: rich>=13.9.4
Requires-Dist: typer>=0.15.1
